cronk/__init__.py
cronk/cron_to_json.py
cronk/json_routine.py
cronk/json_to_cron.py
cronk-0.0.19.dist-info/licenses/LICENSE
cronk-0.0.19.dist-info/METADATA
cronk-0.0.19.dist-info/WHEEL
cronk-0.0.19.dist-info/top_level.txt
cronk-0.0.19.dist-info/RECORD
