Metadata-Version: 2.4
Name: cronk
Version: 0.0.19
Summary: A crontab-json translator
Author-email: "(Fiction) Alice Doe" <alice@cottonwood.edu>, "(Real) Pedro Kaj Kjellerup Nacht" <pnacht@google.com>
Maintainer-email: "(Fiction) Alice Doe" <alice@cottonwood.edu>, "(Real) Pedro Kaj Kjellerup Nacht" <pnacht@google.com>
Project-URL: Homepage, https://github.com/TK_BLOG_URL
Project-URL: Bug Reports, https://github.com/nebraska-dev/cronk/issues
Project-URL: Source, https://github.com/nebraska-dev/cronk/
Keywords: json,cron,crontab
Classifier: Development Status :: 2 - Pre-Alpha
Classifier: Intended Audience :: Education
Classifier: Topic :: Software Development
Classifier: Programming Language :: Python :: 3
Classifier: Programming Language :: Python :: 3.7
Classifier: Programming Language :: Python :: 3.8
Classifier: Programming Language :: Python :: 3.9
Classifier: Programming Language :: Python :: 3.10
Classifier: Programming Language :: Python :: 3.11
Classifier: Programming Language :: Python :: 3 :: Only
Requires-Python: >=3.7
License-File: LICENSE
Requires-Dist: loguru==0.5.2
Requires-Dist: babel==2.9.0
Dynamic: license-file
